{
    "yearFile": 2024,
    "monthFile": 6,
    "folderFile": 99,
    "horariosDataFile": [
        {
            "time": "08:30",
            "rep": "cocococ",
            "vol": "20"
        },
        {
            "time": "11:11",
            "rep": "555",
            "vol": "19"
        },
        {
            "time": "11:11",
            "rep": "59s",
            "vol": "14"
        },
        {
            "time": "11:11",
            "rep": "47",
            "vol": "16"
        },
        {
            "time": "11:11",
            "rep": "98",
            "vol": "23"
        },
        {
            "time": "11:11",
            "rep": "88m",
            "vol": "18"
        }
    ],
    "festDataFile": [
        {
            "st": "2024-06-07",
            "ed": "2024-06-10"
        },
        {
            "st": "2024-06-05",
            "ed": "2024-06-05"
        },
        {
            "st": "2024-06-12",
            "ed": "2024-06-12"
        },
        {
            "st": "2024-06-19",
            "ed": "2024-06-19"
        }
    ]
}